py2glua/__init__.py
py2glua/cli.py
py2glua/config.py
py2glua/_cli/__init__.py
py2glua/_cli/logging_setup.py
py2glua/_lang/__init__.py
py2glua/_lang/etc.py
py2glua/_lang/lua_emiter.py
py2glua/_lang/compiler/__init__.py
py2glua/_lang/compiler/cache.py
py2glua/_lang/compiler/compiler.py
py2glua/_lang/compiler/import_resolver.py
py2glua/_lang/compiler/file_pass/__init__.py
py2glua/_lang/compiler/file_pass/attach_decorators.py
py2glua/_lang/compiler/file_pass/directive_stub.py
py2glua/_lang/compiler/file_pass/normalize_import.py
py2glua/_lang/compiler/file_pass/strip_directive.py
py2glua/_lang/compiler/project_pass/__init__.py
py2glua/_lang/compiler/project_pass/lower_class_table.py
py2glua/_lang/parse/__init__.py
py2glua/_lang/parse/py_logic_block_builder.py
py2glua/_lang/parse/py_parser.py
py2glua/_lang/py/__init__.py
py2glua/_lang/py/build_context.py
py2glua/_lang/py/ir_builder.py
py2glua/_lang/py/ir_dataclass.py
py2glua/_lang/py/builders/__init__.py
py2glua/_lang/py/builders/branch_builder.py
py2glua/_lang/py/builders/class_builder.py
py2glua/_lang/py/builders/comment_builder.py
py2glua/_lang/py/builders/decorator_builder.py
py2glua/_lang/py/builders/function_builder.py
py2glua/_lang/py/builders/import_builder.py
py2glua/_lang/py/builders/loop_builder.py
py2glua/_lang/py/builders/pass_builder.py
py2glua/_lang/py/builders/return_builder.py
py2glua/_lang/py/builders/statement_builder.py
py2glua/_lang/py/builders/with_builder.py
py2glua/glua/__init__.py
py2glua/glua/directive_compiler.py
py2glua/glua/globals.py
py2glua/glua/realm.py
py2glua/glua/type.py
py2glua/glua/unsafe.py
py2glua-0.0.1a2.dist-info/licenses/LICENSE
tests/__init__.py
tests/lang/__init__.py
tests/lang/parse/__init__.py
tests/lang/parse/test_logic_block_builder.py
tests/lang/parse/test_parser.py
py2glua-0.0.1a2.dist-info/METADATA
py2glua-0.0.1a2.dist-info/WHEEL
py2glua-0.0.1a2.dist-info/entry_points.txt
py2glua-0.0.1a2.dist-info/top_level.txt
py2glua-0.0.1a2.dist-info/RECORD
