Metadata-Version: 2.4
Name: py2glua
Version: 0.0.1a2
Summary: Transpiler from Python to GLua
Author: Cain
License:                     GNU GENERAL PUBLIC LICENSE
Project-URL: homepage, https://github.com/py-love-gmod/py2glua
Requires-Python: >=3.13
License-File: LICENSE
Requires-Dist: colorama
Dynamic: license-file
